wintertoo/__init__.py
wintertoo/database.py
wintertoo/errors.py
wintertoo/fields.py
wintertoo/schedule.py
wintertoo/submit.py
wintertoo/utils.py
wintertoo/validate.py
wintertoo/data/__init__.py
wintertoo/data/observing_request_schema.json
wintertoo/data/summer_fields.txt
wintertoo/data/winter_fields.txt
wintertoo/models/__init__.py
wintertoo/models/image.py
wintertoo/models/program.py
wintertoo/models/too.py
wintertoo-1.9.1.dist-info/licenses/LICENSE
wintertoo-1.9.1.dist-info/METADATA
wintertoo-1.9.1.dist-info/WHEEL
wintertoo-1.9.1.dist-info/top_level.txt
wintertoo-1.9.1.dist-info/RECORD
