Metadata-Version: 2.4
Name: wintertoo
Version: 1.9.1
Author-email: Robert Stein <rdstein@caltech.edu>, Danielle Frostig <frostig@mit.edu>, Viraj Karambelkar <viraj@astro.caltech.edu>
License: MIT
Project-URL: homepage, https://github.com/winter-telescope/wintertoo
Classifier: Programming Language :: Python :: 3
Classifier: Programming Language :: Python :: 3.10
Classifier: Programming Language :: Python :: 3.11
Classifier: Intended Audience :: Science/Research
Classifier: Intended Audience :: End Users/Desktop
Classifier: Intended Audience :: Developers
Classifier: Natural Language :: English
Classifier: Topic :: Scientific/Engineering
Classifier: Topic :: Scientific/Engineering :: Astronomy
Classifier: Topic :: Scientific/Engineering :: Physics
Classifier: Operating System :: POSIX
Classifier: Operating System :: Unix
Classifier: Operating System :: MacOS
Requires-Python: >=3.10
License-File: LICENSE
Requires-Dist: pandas<3.0.0
Requires-Dist: astropy>=6.0.0
Requires-Dist: astroplan>=0.10
Requires-Dist: matplotlib
Requires-Dist: numpy
Requires-Dist: pytz
Requires-Dist: jsonschema
Requires-Dist: sqlalchemy
Requires-Dist: pydantic>=2.2.0
Requires-Dist: pre-commit
Requires-Dist: bcrypt
Requires-Dist: psycopg
Requires-Dist: psycopg-binary
Provides-Extra: dev
Requires-Dist: black==26.1.0; extra == "dev"
Requires-Dist: isort>=7.0.0; extra == "dev"
Requires-Dist: pylint>=3.0.0; extra == "dev"
Requires-Dist: coveralls; extra == "dev"
Dynamic: license-file
